// 
// Decompiled by Procyon v0.5.36
// 

package com.flurry.sdk;

import java.io.IOException;
import java.util.Map;
import java.util.List;

public class jd
{
    private static final String b;
    public byte[] a;
    
    static {
        b = jd.class.getSimpleName();
    }
    
    public jd(final String p0, final String p1, final boolean p2, final boolean p3, final long p4, final long p5, final List<jf> p6, final Map<jt, byte[]> p7, final Map<String, List<String>> p8, final Map<String, List<String>> p9, final Map<String, Map<String, String>> p10, final long p11) throws IOException {
        // 
        // This method could not be decompiled.
        // 
        // Original Bytecode:
        // 
        //     1: invokespecial   java/lang/Object.<init>:()V
        //     4: aload_0        
        //     5: aconst_null    
        //     6: putfield        com/flurry/sdk/jd.a:[B
        //     9: aconst_null    
        //    10: astore          16
        //    12: new             Lcom/flurry/sdk/ke;
        //    15: astore          17
        //    17: aload           17
        //    19: invokespecial   com/flurry/sdk/ke.<init>:()V
        //    22: new             Ljava/io/ByteArrayOutputStream;
        //    25: astore          18
        //    27: aload           18
        //    29: invokespecial   java/io/ByteArrayOutputStream.<init>:()V
        //    32: new             Ljava/security/DigestOutputStream;
        //    35: astore          19
        //    37: aload           19
        //    39: aload           18
        //    41: aload           17
        //    43: invokespecial   java/security/DigestOutputStream.<init>:(Ljava/io/OutputStream;Ljava/security/MessageDigest;)V
        //    46: new             Ljava/io/DataOutputStream;
        //    49: astore          20
        //    51: aload           20
        //    53: aload           19
        //    55: invokespecial   java/io/DataOutputStream.<init>:(Ljava/io/OutputStream;)V
        //    58: aload           20
        //    60: bipush          30
        //    62: invokevirtual   java/io/DataOutputStream.writeShort:(I)V
        //    65: aload           20
        //    67: iconst_0       
        //    68: invokevirtual   java/io/DataOutputStream.writeShort:(I)V
        //    71: aload           20
        //    73: lconst_0       
        //    74: invokevirtual   java/io/DataOutputStream.writeLong:(J)V
        //    77: aload           20
        //    79: iconst_0       
        //    80: invokevirtual   java/io/DataOutputStream.writeShort:(I)V
        //    83: aload           20
        //    85: iconst_3       
        //    86: invokevirtual   java/io/DataOutputStream.writeShort:(I)V
        //    89: aload           20
        //    91: invokestatic    com/flurry/sdk/jz.a:()I
        //    94: invokevirtual   java/io/DataOutputStream.writeShort:(I)V
        //    97: aload           20
        //    99: lload           14
        //   101: invokevirtual   java/io/DataOutputStream.writeLong:(J)V
        //   104: aload           20
        //   106: aload_1        
        //   107: invokevirtual   java/io/DataOutputStream.writeUTF:(Ljava/lang/String;)V
        //   110: aload           20
        //   112: aload_2        
        //   113: invokevirtual   java/io/DataOutputStream.writeUTF:(Ljava/lang/String;)V
        //   116: aload           20
        //   118: aload           10
        //   120: invokeinterface java/util/Map.size:()I
        //   125: invokevirtual   java/io/DataOutputStream.writeShort:(I)V
        //   128: aload           10
        //   130: invokeinterface java/util/Map.entrySet:()Ljava/util/Set;
        //   135: invokeinterface java/util/Set.iterator:()Ljava/util/Iterator;
        //   140: astore_1       
        //   141: aload_1        
        //   142: invokeinterface java/util/Iterator.hasNext:()Z
        //   147: ifeq            230
        //   150: aload_1        
        //   151: invokeinterface java/util/Iterator.next:()Ljava/lang/Object;
        //   156: checkcast       Ljava/util/Map$Entry;
        //   159: astore_2       
        //   160: aload           20
        //   162: aload_2        
        //   163: invokeinterface java/util/Map$Entry.getKey:()Ljava/lang/Object;
        //   168: checkcast       Lcom/flurry/sdk/jt;
        //   171: getfield        com/flurry/sdk/jt.c:I
        //   174: invokevirtual   java/io/DataOutputStream.writeShort:(I)V
        //   177: aload_2        
        //   178: invokeinterface java/util/Map$Entry.getValue:()Ljava/lang/Object;
        //   183: checkcast       [B
        //   186: astore_2       
        //   187: aload           20
        //   189: aload_2        
        //   190: arraylength    
        //   191: invokevirtual   java/io/DataOutputStream.writeShort:(I)V
        //   194: aload           20
        //   196: aload_2        
        //   197: invokevirtual   java/io/DataOutputStream.write:([B)V
        //   200: goto            141
        //   203: astore_2       
        //   204: aload           20
        //   206: astore_1       
        //   207: bipush          6
        //   209: getstatic       com/flurry/sdk/jd.b:Ljava/lang/String;
        //   212: ldc             "Error when generating report"
        //   214: aload_2        
        //   215: invokestatic    com/flurry/sdk/km.a:(ILjava/lang/String;Ljava/lang/String;Ljava/lang/Throwable;)V
        //   218: aload_1        
        //   219: invokestatic    com/flurry/sdk/ly.a:(Ljava/io/Closeable;)V
        //   222: aconst_null    
        //   223: astore_1       
        //   224: aload_0        
        //   225: aload_1        
        //   226: putfield        com/flurry/sdk/jd.a:[B
        //   229: return         
        //   230: aload           20
        //   232: iconst_0       
        //   233: invokevirtual   java/io/DataOutputStream.writeByte:(I)V
        //   236: aload           20
        //   238: iload_3        
        //   239: invokevirtual   java/io/DataOutputStream.writeBoolean:(Z)V
        //   242: aload           20
        //   244: iload           4
        //   246: invokevirtual   java/io/DataOutputStream.writeBoolean:(Z)V
        //   249: aload           20
        //   251: lload           5
        //   253: invokevirtual   java/io/DataOutputStream.writeLong:(J)V
        //   256: aload           20
        //   258: lload           7
        //   260: invokevirtual   java/io/DataOutputStream.writeLong:(J)V
        //   263: aload           20
        //   265: bipush          6
        //   267: invokevirtual   java/io/DataOutputStream.writeShort:(I)V
        //   270: aload           20
        //   272: ldc             "device.model"
        //   274: invokevirtual   java/io/DataOutputStream.writeUTF:(Ljava/lang/String;)V
        //   277: aload           20
        //   279: getstatic       android/os/Build.MODEL:Ljava/lang/String;
        //   282: invokevirtual   java/io/DataOutputStream.writeUTF:(Ljava/lang/String;)V
        //   285: aload           20
        //   287: iconst_0       
        //   288: invokevirtual   java/io/DataOutputStream.writeByte:(I)V
        //   291: aload           20
        //   293: ldc             "build.brand"
        //   295: invokevirtual   java/io/DataOutputStream.writeUTF:(Ljava/lang/String;)V
        //   298: aload           20
        //   300: getstatic       android/os/Build.BRAND:Ljava/lang/String;
        //   303: invokevirtual   java/io/DataOutputStream.writeUTF:(Ljava/lang/String;)V
        //   306: aload           20
        //   308: iconst_0       
        //   309: invokevirtual   java/io/DataOutputStream.writeByte:(I)V
        //   312: aload           20
        //   314: ldc             "build.id"
        //   316: invokevirtual   java/io/DataOutputStream.writeUTF:(Ljava/lang/String;)V
        //   319: aload           20
        //   321: getstatic       android/os/Build.ID:Ljava/lang/String;
        //   324: invokevirtual   java/io/DataOutputStream.writeUTF:(Ljava/lang/String;)V
        //   327: aload           20
        //   329: iconst_0       
        //   330: invokevirtual   java/io/DataOutputStream.writeByte:(I)V
        //   333: aload           20
        //   335: ldc             "version.release"
        //   337: invokevirtual   java/io/DataOutputStream.writeUTF:(Ljava/lang/String;)V
        //   340: aload           20
        //   342: getstatic       android/os/Build$VERSION.RELEASE:Ljava/lang/String;
        //   345: invokevirtual   java/io/DataOutputStream.writeUTF:(Ljava/lang/String;)V
        //   348: aload           20
        //   350: iconst_0       
        //   351: invokevirtual   java/io/DataOutputStream.writeByte:(I)V
        //   354: aload           20
        //   356: ldc             "build.device"
        //   358: invokevirtual   java/io/DataOutputStream.writeUTF:(Ljava/lang/String;)V
        //   361: aload           20
        //   363: getstatic       android/os/Build.DEVICE:Ljava/lang/String;
        //   366: invokevirtual   java/io/DataOutputStream.writeUTF:(Ljava/lang/String;)V
        //   369: aload           20
        //   371: iconst_0       
        //   372: invokevirtual   java/io/DataOutputStream.writeByte:(I)V
        //   375: aload           20
        //   377: ldc             "build.product"
        //   379: invokevirtual   java/io/DataOutputStream.writeUTF:(Ljava/lang/String;)V
        //   382: aload           20
        //   384: getstatic       android/os/Build.PRODUCT:Ljava/lang/String;
        //   387: invokevirtual   java/io/DataOutputStream.writeUTF:(Ljava/lang/String;)V
        //   390: aload           20
        //   392: iconst_0       
        //   393: invokevirtual   java/io/DataOutputStream.writeByte:(I)V
        //   396: aload           11
        //   398: ifnull          683
        //   401: aload           11
        //   403: invokeinterface java/util/Map.keySet:()Ljava/util/Set;
        //   408: invokeinterface java/util/Set.size:()I
        //   413: istore          21
        //   415: aload           20
        //   417: iload           21
        //   419: invokevirtual   java/io/DataOutputStream.writeShort:(I)V
        //   422: aload           11
        //   424: ifnull          689
        //   427: iconst_3       
        //   428: getstatic       com/flurry/sdk/jd.b:Ljava/lang/String;
        //   431: ldc             "sending referrer values because it exists"
        //   433: invokestatic    com/flurry/sdk/km.a:(ILjava/lang/String;Ljava/lang/String;)V
        //   436: aload           11
        //   438: invokeinterface java/util/Map.entrySet:()Ljava/util/Set;
        //   443: invokeinterface java/util/Set.iterator:()Ljava/util/Iterator;
        //   448: astore_1       
        //   449: aload_1        
        //   450: invokeinterface java/util/Iterator.hasNext:()Z
        //   455: ifeq            689
        //   458: aload_1        
        //   459: invokeinterface java/util/Iterator.next:()Ljava/lang/Object;
        //   464: checkcast       Ljava/util/Map$Entry;
        //   467: astore_2       
        //   468: getstatic       com/flurry/sdk/jd.b:Ljava/lang/String;
        //   471: astore          11
        //   473: new             Ljava/lang/StringBuilder;
        //   476: astore          10
        //   478: aload           10
        //   480: ldc             "Referrer Entry:  "
        //   482: invokespecial   java/lang/StringBuilder.<init>:(Ljava/lang/String;)V
        //   485: iconst_3       
        //   486: aload           11
        //   488: aload           10
        //   490: aload_2        
        //   491: invokeinterface java/util/Map$Entry.getKey:()Ljava/lang/Object;
        //   496: checkcast       Ljava/lang/String;
        //   499: invokevirtual   java/lang/StringBuilder.append:(Ljava/lang/String;)Ljava/lang/StringBuilder;
        //   502: ldc             "="
        //   504: invokevirtual   java/lang/StringBuilder.append:(Ljava/lang/String;)Ljava/lang/StringBuilder;
        //   507: aload_2        
        //   508: invokeinterface java/util/Map$Entry.getValue:()Ljava/lang/Object;
        //   513: invokevirtual   java/lang/StringBuilder.append:(Ljava/lang/Object;)Ljava/lang/StringBuilder;
        //   516: invokevirtual   java/lang/StringBuilder.toString:()Ljava/lang/String;
        //   519: invokestatic    com/flurry/sdk/km.a:(ILjava/lang/String;Ljava/lang/String;)V
        //   522: aload           20
        //   524: aload_2        
        //   525: invokeinterface java/util/Map$Entry.getKey:()Ljava/lang/Object;
        //   530: checkcast       Ljava/lang/String;
        //   533: invokevirtual   java/io/DataOutputStream.writeUTF:(Ljava/lang/String;)V
        //   536: getstatic       com/flurry/sdk/jd.b:Ljava/lang/String;
        //   539: astore          11
        //   541: new             Ljava/lang/StringBuilder;
        //   544: astore          10
        //   546: aload           10
        //   548: ldc             "referrer key is :"
        //   550: invokespecial   java/lang/StringBuilder.<init>:(Ljava/lang/String;)V
        //   553: iconst_3       
        //   554: aload           11
        //   556: aload           10
        //   558: aload_2        
        //   559: invokeinterface java/util/Map$Entry.getKey:()Ljava/lang/Object;
        //   564: checkcast       Ljava/lang/String;
        //   567: invokevirtual   java/lang/StringBuilder.append:(Ljava/lang/String;)Ljava/lang/StringBuilder;
        //   570: invokevirtual   java/lang/StringBuilder.toString:()Ljava/lang/String;
        //   573: invokestatic    com/flurry/sdk/km.a:(ILjava/lang/String;Ljava/lang/String;)V
        //   576: aload           20
        //   578: aload_2        
        //   579: invokeinterface java/util/Map$Entry.getValue:()Ljava/lang/Object;
        //   584: checkcast       Ljava/util/List;
        //   587: invokeinterface java/util/List.size:()I
        //   592: invokevirtual   java/io/DataOutputStream.writeShort:(I)V
        //   595: aload_2        
        //   596: invokeinterface java/util/Map$Entry.getValue:()Ljava/lang/Object;
        //   601: checkcast       Ljava/util/List;
        //   604: invokeinterface java/util/List.iterator:()Ljava/util/Iterator;
        //   609: astore          16
        //   611: aload           16
        //   613: invokeinterface java/util/Iterator.hasNext:()Z
        //   618: ifeq            449
        //   621: aload           16
        //   623: invokeinterface java/util/Iterator.next:()Ljava/lang/Object;
        //   628: checkcast       Ljava/lang/String;
        //   631: astore          10
        //   633: aload           20
        //   635: aload           10
        //   637: invokevirtual   java/io/DataOutputStream.writeUTF:(Ljava/lang/String;)V
        //   640: getstatic       com/flurry/sdk/jd.b:Ljava/lang/String;
        //   643: astore          11
        //   645: new             Ljava/lang/StringBuilder;
        //   648: astore_2       
        //   649: aload_2        
        //   650: ldc             "referrer value is :"
        //   652: invokespecial   java/lang/StringBuilder.<init>:(Ljava/lang/String;)V
        //   655: iconst_3       
        //   656: aload           11
        //   658: aload_2        
        //   659: aload           10
        //   661: invokevirtual   java/lang/StringBuilder.append:(Ljava/lang/String;)Ljava/lang/StringBuilder;
        //   664: invokevirtual   java/lang/StringBuilder.toString:()Ljava/lang/String;
        //   667: invokestatic    com/flurry/sdk/km.a:(ILjava/lang/String;Ljava/lang/String;)V
        //   670: goto            611
        //   673: astore_1       
        //   674: aload           20
        //   676: astore_2       
        //   677: aload_2        
        //   678: invokestatic    com/flurry/sdk/ly.a:(Ljava/io/Closeable;)V
        //   681: aload_1        
        //   682: athrow         
        //   683: iconst_0       
        //   684: istore          21
        //   686: goto            415
        //   689: aload           20
        //   691: iconst_0       
        //   692: invokevirtual   java/io/DataOutputStream.writeBoolean:(Z)V
        //   695: aload           12
        //   697: ifnull          946
        //   700: aload           12
        //   702: invokeinterface java/util/Map.keySet:()Ljava/util/Set;
        //   707: invokeinterface java/util/Set.size:()I
        //   712: istore          21
        //   714: getstatic       com/flurry/sdk/jd.b:Ljava/lang/String;
        //   717: astore_2       
        //   718: new             Ljava/lang/StringBuilder;
        //   721: astore_1       
        //   722: aload_1        
        //   723: ldc             "optionsMapSize is:  "
        //   725: invokespecial   java/lang/StringBuilder.<init>:(Ljava/lang/String;)V
        //   728: iconst_3       
        //   729: aload_2        
        //   730: aload_1        
        //   731: iload           21
        //   733: invokevirtual   java/lang/StringBuilder.append:(I)Ljava/lang/StringBuilder;
        //   736: invokevirtual   java/lang/StringBuilder.toString:()Ljava/lang/String;
        //   739: invokestatic    com/flurry/sdk/km.a:(ILjava/lang/String;Ljava/lang/String;)V
        //   742: aload           20
        //   744: iload           21
        //   746: invokevirtual   java/io/DataOutputStream.writeShort:(I)V
        //   749: aload           12
        //   751: ifnull          952
        //   754: iconst_3       
        //   755: getstatic       com/flurry/sdk/jd.b:Ljava/lang/String;
        //   758: ldc             "sending launch options"
        //   760: invokestatic    com/flurry/sdk/km.a:(ILjava/lang/String;Ljava/lang/String;)V
        //   763: aload           12
        //   765: invokeinterface java/util/Map.entrySet:()Ljava/util/Set;
        //   770: invokeinterface java/util/Set.iterator:()Ljava/util/Iterator;
        //   775: astore_1       
        //   776: aload_1        
        //   777: invokeinterface java/util/Iterator.hasNext:()Z
        //   782: ifeq            952
        //   785: aload_1        
        //   786: invokeinterface java/util/Iterator.next:()Ljava/lang/Object;
        //   791: checkcast       Ljava/util/Map$Entry;
        //   794: astore_2       
        //   795: getstatic       com/flurry/sdk/jd.b:Ljava/lang/String;
        //   798: astore          11
        //   800: new             Ljava/lang/StringBuilder;
        //   803: astore          10
        //   805: aload           10
        //   807: ldc             "Launch Options Key:  "
        //   809: invokespecial   java/lang/StringBuilder.<init>:(Ljava/lang/String;)V
        //   812: iconst_3       
        //   813: aload           11
        //   815: aload           10
        //   817: aload_2        
        //   818: invokeinterface java/util/Map$Entry.getKey:()Ljava/lang/Object;
        //   823: checkcast       Ljava/lang/String;
        //   826: invokevirtual   java/lang/StringBuilder.append:(Ljava/lang/String;)Ljava/lang/StringBuilder;
        //   829: invokevirtual   java/lang/StringBuilder.toString:()Ljava/lang/String;
        //   832: invokestatic    com/flurry/sdk/km.a:(ILjava/lang/String;Ljava/lang/String;)V
        //   835: aload           20
        //   837: aload_2        
        //   838: invokeinterface java/util/Map$Entry.getKey:()Ljava/lang/Object;
        //   843: checkcast       Ljava/lang/String;
        //   846: invokevirtual   java/io/DataOutputStream.writeUTF:(Ljava/lang/String;)V
        //   849: aload           20
        //   851: aload_2        
        //   852: invokeinterface java/util/Map$Entry.getValue:()Ljava/lang/Object;
        //   857: checkcast       Ljava/util/List;
        //   860: invokeinterface java/util/List.size:()I
        //   865: invokevirtual   java/io/DataOutputStream.writeShort:(I)V
        //   868: aload_2        
        //   869: invokeinterface java/util/Map$Entry.getValue:()Ljava/lang/Object;
        //   874: checkcast       Ljava/util/List;
        //   877: invokeinterface java/util/List.iterator:()Ljava/util/Iterator;
        //   882: astore_2       
        //   883: aload_2        
        //   884: invokeinterface java/util/Iterator.hasNext:()Z
        //   889: ifeq            776
        //   892: aload_2        
        //   893: invokeinterface java/util/Iterator.next:()Ljava/lang/Object;
        //   898: checkcast       Ljava/lang/String;
        //   901: astore          11
        //   903: aload           20
        //   905: aload           11
        //   907: invokevirtual   java/io/DataOutputStream.writeUTF:(Ljava/lang/String;)V
        //   910: getstatic       com/flurry/sdk/jd.b:Ljava/lang/String;
        //   913: astore          10
        //   915: new             Ljava/lang/StringBuilder;
        //   918: astore          12
        //   920: aload           12
        //   922: ldc             "Launch Options value is :"
        //   924: invokespecial   java/lang/StringBuilder.<init>:(Ljava/lang/String;)V
        //   927: iconst_3       
        //   928: aload           10
        //   930: aload           12
        //   932: aload           11
        //   934: invokevirtual   java/lang/StringBuilder.append:(Ljava/lang/String;)Ljava/lang/StringBuilder;
        //   937: invokevirtual   java/lang/StringBuilder.toString:()Ljava/lang/String;
        //   940: invokestatic    com/flurry/sdk/km.a:(ILjava/lang/String;Ljava/lang/String;)V
        //   943: goto            883
        //   946: iconst_0       
        //   947: istore          21
        //   949: goto            714
        //   952: aload           13
        //   954: ifnull          1348
        //   957: aload           13
        //   959: invokeinterface java/util/Map.keySet:()Ljava/util/Set;
        //   964: invokeinterface java/util/Set.size:()I
        //   969: istore          22
        //   971: getstatic       com/flurry/sdk/jd.b:Ljava/lang/String;
        //   974: astore_1       
        //   975: new             Ljava/lang/StringBuilder;
        //   978: astore_2       
        //   979: aload_2        
        //   980: ldc             "numOriginAttributions is:  "
        //   982: invokespecial   java/lang/StringBuilder.<init>:(Ljava/lang/String;)V
        //   985: iconst_3       
        //   986: aload_1        
        //   987: aload_2        
        //   988: iload           21
        //   990: invokevirtual   java/lang/StringBuilder.append:(I)Ljava/lang/StringBuilder;
        //   993: invokevirtual   java/lang/StringBuilder.toString:()Ljava/lang/String;
        //   996: invokestatic    com/flurry/sdk/km.a:(ILjava/lang/String;Ljava/lang/String;)V
        //   999: aload           20
        //  1001: iload           22
        //  1003: invokevirtual   java/io/DataOutputStream.writeShort:(I)V
        //  1006: aload           13
        //  1008: ifnull          1366
        //  1011: aload           13
        //  1013: invokeinterface java/util/Map.entrySet:()Ljava/util/Set;
        //  1018: invokeinterface java/util/Set.iterator:()Ljava/util/Iterator;
        //  1023: astore          10
        //  1025: aload           10
        //  1027: invokeinterface java/util/Iterator.hasNext:()Z
        //  1032: ifeq            1366
        //  1035: aload           10
        //  1037: invokeinterface java/util/Iterator.next:()Ljava/lang/Object;
        //  1042: checkcast       Ljava/util/Map$Entry;
        //  1045: astore_2       
        //  1046: getstatic       com/flurry/sdk/jd.b:Ljava/lang/String;
        //  1049: astore          11
        //  1051: new             Ljava/lang/StringBuilder;
        //  1054: astore_1       
        //  1055: aload_1        
        //  1056: ldc             "Origin Atttribute Key:  "
        //  1058: invokespecial   java/lang/StringBuilder.<init>:(Ljava/lang/String;)V
        //  1061: iconst_3       
        //  1062: aload           11
        //  1064: aload_1        
        //  1065: aload_2        
        //  1066: invokeinterface java/util/Map$Entry.getKey:()Ljava/lang/Object;
        //  1071: checkcast       Ljava/lang/String;
        //  1074: invokevirtual   java/lang/StringBuilder.append:(Ljava/lang/String;)Ljava/lang/StringBuilder;
        //  1077: invokevirtual   java/lang/StringBuilder.toString:()Ljava/lang/String;
        //  1080: invokestatic    com/flurry/sdk/km.a:(ILjava/lang/String;Ljava/lang/String;)V
        //  1083: aload           20
        //  1085: aload_2        
        //  1086: invokeinterface java/util/Map$Entry.getKey:()Ljava/lang/Object;
        //  1091: checkcast       Ljava/lang/String;
        //  1094: invokevirtual   java/io/DataOutputStream.writeUTF:(Ljava/lang/String;)V
        //  1097: aload           20
        //  1099: aload_2        
        //  1100: invokeinterface java/util/Map$Entry.getValue:()Ljava/lang/Object;
        //  1105: checkcast       Ljava/util/Map;
        //  1108: invokeinterface java/util/Map.size:()I
        //  1113: invokevirtual   java/io/DataOutputStream.writeShort:(I)V
        //  1116: getstatic       com/flurry/sdk/jd.b:Ljava/lang/String;
        //  1119: astore          11
        //  1121: new             Ljava/lang/StringBuilder;
        //  1124: astore_1       
        //  1125: aload_1        
        //  1126: ldc             "Origin Attribute Map Size for "
        //  1128: invokespecial   java/lang/StringBuilder.<init>:(Ljava/lang/String;)V
        //  1131: iconst_3       
        //  1132: aload           11
        //  1134: aload_1        
        //  1135: aload_2        
        //  1136: invokeinterface java/util/Map$Entry.getKey:()Ljava/lang/Object;
        //  1141: checkcast       Ljava/lang/String;
        //  1144: invokevirtual   java/lang/StringBuilder.append:(Ljava/lang/String;)Ljava/lang/StringBuilder;
        //  1147: ldc             ":  "
        //  1149: invokevirtual   java/lang/StringBuilder.append:(Ljava/lang/String;)Ljava/lang/StringBuilder;
        //  1152: aload_2        
        //  1153: invokeinterface java/util/Map$Entry.getValue:()Ljava/lang/Object;
        //  1158: checkcast       Ljava/util/Map;
        //  1161: invokeinterface java/util/Map.size:()I
        //  1166: invokevirtual   java/lang/StringBuilder.append:(I)Ljava/lang/StringBuilder;
        //  1169: invokevirtual   java/lang/StringBuilder.toString:()Ljava/lang/String;
        //  1172: invokestatic    com/flurry/sdk/km.a:(ILjava/lang/String;Ljava/lang/String;)V
        //  1175: aload_2        
        //  1176: invokeinterface java/util/Map$Entry.getValue:()Ljava/lang/Object;
        //  1181: checkcast       Ljava/util/Map;
        //  1184: invokeinterface java/util/Map.entrySet:()Ljava/util/Set;
        //  1189: invokeinterface java/util/Set.iterator:()Ljava/util/Iterator;
        //  1194: astore          11
        //  1196: aload           11
        //  1198: invokeinterface java/util/Iterator.hasNext:()Z
        //  1203: ifeq            1025
        //  1206: aload           11
        //  1208: invokeinterface java/util/Iterator.next:()Ljava/lang/Object;
        //  1213: checkcast       Ljava/util/Map$Entry;
        //  1216: astore          12
        //  1218: getstatic       com/flurry/sdk/jd.b:Ljava/lang/String;
        //  1221: astore          13
        //  1223: new             Ljava/lang/StringBuilder;
        //  1226: astore_1       
        //  1227: aload_1        
        //  1228: ldc             "Origin Atttribute for "
        //  1230: invokespecial   java/lang/StringBuilder.<init>:(Ljava/lang/String;)V
        //  1233: iconst_3       
        //  1234: aload           13
        //  1236: aload_1        
        //  1237: aload_2        
        //  1238: invokeinterface java/util/Map$Entry.getKey:()Ljava/lang/Object;
        //  1243: checkcast       Ljava/lang/String;
        //  1246: invokevirtual   java/lang/StringBuilder.append:(Ljava/lang/String;)Ljava/lang/StringBuilder;
        //  1249: ldc             ":  "
        //  1251: invokevirtual   java/lang/StringBuilder.append:(Ljava/lang/String;)Ljava/lang/StringBuilder;
        //  1254: aload           12
        //  1256: invokeinterface java/util/Map$Entry.getKey:()Ljava/lang/Object;
        //  1261: checkcast       Ljava/lang/String;
        //  1264: invokevirtual   java/lang/StringBuilder.append:(Ljava/lang/String;)Ljava/lang/StringBuilder;
        //  1267: ldc             ":"
        //  1269: invokevirtual   java/lang/StringBuilder.append:(Ljava/lang/String;)Ljava/lang/StringBuilder;
        //  1272: aload           12
        //  1274: invokeinterface java/util/Map$Entry.getValue:()Ljava/lang/Object;
        //  1279: checkcast       Ljava/lang/String;
        //  1282: invokevirtual   java/lang/StringBuilder.append:(Ljava/lang/String;)Ljava/lang/StringBuilder;
        //  1285: invokevirtual   java/lang/StringBuilder.toString:()Ljava/lang/String;
        //  1288: invokestatic    com/flurry/sdk/km.a:(ILjava/lang/String;Ljava/lang/String;)V
        //  1291: aload           12
        //  1293: invokeinterface java/util/Map$Entry.getKey:()Ljava/lang/Object;
        //  1298: ifnull          1354
        //  1301: aload           12
        //  1303: invokeinterface java/util/Map$Entry.getKey:()Ljava/lang/Object;
        //  1308: checkcast       Ljava/lang/String;
        //  1311: astore_1       
        //  1312: aload           20
        //  1314: aload_1        
        //  1315: invokevirtual   java/io/DataOutputStream.writeUTF:(Ljava/lang/String;)V
        //  1318: aload           12
        //  1320: invokeinterface java/util/Map$Entry.getValue:()Ljava/lang/Object;
        //  1325: ifnull          1360
        //  1328: aload           12
        //  1330: invokeinterface java/util/Map$Entry.getValue:()Ljava/lang/Object;
        //  1335: checkcast       Ljava/lang/String;
        //  1338: astore_1       
        //  1339: aload           20
        //  1341: aload_1        
        //  1342: invokevirtual   java/io/DataOutputStream.writeUTF:(Ljava/lang/String;)V
        //  1345: goto            1196
        //  1348: iconst_0       
        //  1349: istore          22
        //  1351: goto            971
        //  1354: ldc             ""
        //  1356: astore_1       
        //  1357: goto            1312
        //  1360: ldc             ""
        //  1362: astore_1       
        //  1363: goto            1339
        //  1366: aload           20
        //  1368: invokestatic    com/flurry/sdk/jy.a:()Lcom/flurry/sdk/jy;
        //  1371: getfield        com/flurry/sdk/jy.a:Landroid/content/Context;
        //  1374: invokestatic    com/flurry/sdk/lv.a:(Landroid/content/Context;)Ljava/lang/String;
        //  1377: invokevirtual   java/io/DataOutputStream.writeUTF:(Ljava/lang/String;)V
        //  1380: aload           20
        //  1382: aload           9
        //  1384: invokeinterface java/util/List.size:()I
        //  1389: invokevirtual   java/io/DataOutputStream.writeShort:(I)V
        //  1392: aload           9
        //  1394: invokeinterface java/util/List.iterator:()Ljava/util/Iterator;
        //  1399: astore_1       
        //  1400: aload_1        
        //  1401: invokeinterface java/util/Iterator.hasNext:()Z
        //  1406: ifeq            1429
        //  1409: aload           20
        //  1411: aload_1        
        //  1412: invokeinterface java/util/Iterator.next:()Ljava/lang/Object;
        //  1417: checkcast       Lcom/flurry/sdk/jf;
        //  1420: getfield        com/flurry/sdk/jf.a:[B
        //  1423: invokevirtual   java/io/DataOutputStream.write:([B)V
        //  1426: goto            1400
        //  1429: aload           20
        //  1431: iconst_0       
        //  1432: invokevirtual   java/io/DataOutputStream.writeShort:(I)V
        //  1435: aload           19
        //  1437: iconst_0       
        //  1438: invokevirtual   java/security/DigestOutputStream.on:(Z)V
        //  1441: aload           20
        //  1443: aload           17
        //  1445: invokevirtual   com/flurry/sdk/ke.a:()[B
        //  1448: invokevirtual   java/io/DataOutputStream.write:([B)V
        //  1451: aload           20
        //  1453: invokevirtual   java/io/DataOutputStream.close:()V
        //  1456: aload           18
        //  1458: invokevirtual   java/io/ByteArrayOutputStream.toByteArray:()[B
        //  1461: astore_1       
        //  1462: aload           20
        //  1464: invokestatic    com/flurry/sdk/ly.a:(Ljava/io/Closeable;)V
        //  1467: goto            224
        //  1470: astore_1       
        //  1471: aconst_null    
        //  1472: astore_2       
        //  1473: goto            677
        //  1476: astore          9
        //  1478: aload_1        
        //  1479: astore_2       
        //  1480: aload           9
        //  1482: astore_1       
        //  1483: goto            677
        //  1486: astore_2       
        //  1487: aload           16
        //  1489: astore_1       
        //  1490: goto            207
        //    Exceptions:
        //  throws java.io.IOException
        //    Signature:
        //  (Ljava/lang/String;Ljava/lang/String;ZZJJLjava/util/List<Lcom/flurry/sdk/jf;>;Ljava/util/Map<Lcom/flurry/sdk/jt;[B>;Ljava/util/Map<Ljava/lang/String;Ljava/util/List<Ljava/lang/String;>;>;Ljava/util/Map<Ljava/lang/String;Ljava/util/List<Ljava/lang/String;>;>;Ljava/util/Map<Ljava/lang/String;Ljava/util/Map<Ljava/lang/String;Ljava/lang/String;>;>;J)V
        //    Exceptions:
        //  Try           Handler
        //  Start  End    Start  End    Type                 
        //  -----  -----  -----  -----  ---------------------
        //  12     58     1486   1493   Ljava/lang/Throwable;
        //  12     58     1470   1476   Any
        //  58     141    203    207    Ljava/lang/Throwable;
        //  58     141    673    677    Any
        //  141    200    203    207    Ljava/lang/Throwable;
        //  141    200    673    677    Any
        //  207    218    1476   1486   Any
        //  230    396    203    207    Ljava/lang/Throwable;
        //  230    396    673    677    Any
        //  401    415    203    207    Ljava/lang/Throwable;
        //  401    415    673    677    Any
        //  415    422    203    207    Ljava/lang/Throwable;
        //  415    422    673    677    Any
        //  427    449    203    207    Ljava/lang/Throwable;
        //  427    449    673    677    Any
        //  449    611    203    207    Ljava/lang/Throwable;
        //  449    611    673    677    Any
        //  611    670    203    207    Ljava/lang/Throwable;
        //  611    670    673    677    Any
        //  689    695    203    207    Ljava/lang/Throwable;
        //  689    695    673    677    Any
        //  700    714    203    207    Ljava/lang/Throwable;
        //  700    714    673    677    Any
        //  714    749    203    207    Ljava/lang/Throwable;
        //  714    749    673    677    Any
        //  754    776    203    207    Ljava/lang/Throwable;
        //  754    776    673    677    Any
        //  776    883    203    207    Ljava/lang/Throwable;
        //  776    883    673    677    Any
        //  883    943    203    207    Ljava/lang/Throwable;
        //  883    943    673    677    Any
        //  957    971    203    207    Ljava/lang/Throwable;
        //  957    971    673    677    Any
        //  971    1006   203    207    Ljava/lang/Throwable;
        //  971    1006   673    677    Any
        //  1011   1025   203    207    Ljava/lang/Throwable;
        //  1011   1025   673    677    Any
        //  1025   1196   203    207    Ljava/lang/Throwable;
        //  1025   1196   673    677    Any
        //  1196   1312   203    207    Ljava/lang/Throwable;
        //  1196   1312   673    677    Any
        //  1312   1339   203    207    Ljava/lang/Throwable;
        //  1312   1339   673    677    Any
        //  1339   1345   203    207    Ljava/lang/Throwable;
        //  1339   1345   673    677    Any
        //  1366   1400   203    207    Ljava/lang/Throwable;
        //  1366   1400   673    677    Any
        //  1400   1426   203    207    Ljava/lang/Throwable;
        //  1400   1426   673    677    Any
        //  1429   1462   203    207    Ljava/lang/Throwable;
        //  1429   1462   673    677    Any
        // 
        // The error that occurred was:
        // 
        // java.lang.IllegalStateException: Expression is linked from several locations: Label_0207:
        //     at com.strobel.decompiler.ast.Error.expressionLinkedFromMultipleLocations(Error.java:27)
        //     at com.strobel.decompiler.ast.AstOptimizer.mergeDisparateObjectInitializations(AstOptimizer.java:2596)
        //     at com.strobel.decompiler.ast.AstOptimizer.optimize(AstOptimizer.java:235)
        //     at com.strobel.decompiler.ast.AstOptimizer.optimize(AstOptimizer.java:42)
        //     at com.strobel.decompiler.languages.java.ast.AstMethodBodyBuilder.createMethodBody(AstMethodBodyBuilder.java:214)
        //     at com.strobel.decompiler.languages.java.ast.AstMethodBodyBuilder.createMethodBody(AstMethodBodyBuilder.java:99)
        //     at com.strobel.decompiler.languages.java.ast.AstBuilder.createMethodBody(AstBuilder.java:782)
        //     at com.strobel.decompiler.languages.java.ast.AstBuilder.createConstructor(AstBuilder.java:713)
        //     at com.strobel.decompiler.languages.java.ast.AstBuilder.addTypeMembers(AstBuilder.java:549)
        //     at com.strobel.decompiler.languages.java.ast.AstBuilder.createTypeCore(AstBuilder.java:519)
        //     at com.strobel.decompiler.languages.java.ast.AstBuilder.createTypeNoCache(AstBuilder.java:161)
        //     at com.strobel.decompiler.languages.java.ast.AstBuilder.createType(AstBuilder.java:150)
        //     at com.strobel.decompiler.languages.java.ast.AstBuilder.addType(AstBuilder.java:125)
        //     at com.strobel.decompiler.languages.java.JavaLanguage.buildAst(JavaLanguage.java:71)
        //     at com.strobel.decompiler.languages.java.JavaLanguage.decompileType(JavaLanguage.java:59)
        //     at com.strobel.decompiler.DecompilerDriver.decompileType(DecompilerDriver.java:330)
        //     at com.strobel.decompiler.DecompilerDriver.decompileJar(DecompilerDriver.java:251)
        //     at com.strobel.decompiler.DecompilerDriver.main(DecompilerDriver.java:126)
        // 
        throw new IllegalStateException("An error occurred while decompiling this method.");
    }
}
